setup.cfg
setup.py
starflyer/__init__.py
starflyer/app.py
starflyer/decorators.py
starflyer/events.py
starflyer/exceptions.py
starflyer/handler.py
starflyer/helpers.py
starflyer/modules.py
starflyer/scripts.py
starflyer/sessions.py
starflyer/static.py
starflyer/templating.py
starflyer/wrappers.py
starflyer.egg-info/PKG-INFO
starflyer.egg-info/SOURCES.txt
starflyer.egg-info/dependency_links.txt
starflyer.egg-info/entry_points.txt
starflyer.egg-info/not-zip-safe
starflyer.egg-info/requires.txt
starflyer.egg-info/top_level.txt
starflyer/contrib/__init__.py
starflyer/contrib/loghandlers.py
starflyer/contrib/snippets.py
starflyer/tests/__init__.py
starflyer/tests/conftest.py
starflyer/tests/test_app_basics.py
starflyer/tests/test_attribute_mapper.py
starflyer/tests/test_class_overrides.py
starflyer/tests/test_configuration.py
starflyer/tests/test_errorhandling.py
starflyer/tests/test_modules.py
starflyer/tests/test_process_hooks.py
starflyer/tests/test_sessions.py
starflyer/tests/test_templating.py
starflyer/tests/mods/__init__.py
starflyer/tests/mods/testmodule.py