Metadata-Version: 1.0
Name: starflyer
Version: 2.1
Summary: Starflyer web framework
Home-page: UNKNOWN
Author: COM.lounge
Author-email: info@comlounge.net
License: BSD
Platform: UNKNOWN
